dsmtpd/__init__.py
dsmtpd/__main__.py
dsmtpd/_dsmtpd.py
dsmtpd-1.2.0.dist-info/licenses/AUTHORS
dsmtpd-1.2.0.dist-info/licenses/LICENSE
dsmtpd-1.2.0.dist-info/METADATA
dsmtpd-1.2.0.dist-info/WHEEL
dsmtpd-1.2.0.dist-info/entry_points.txt
dsmtpd-1.2.0.dist-info/top_level.txt
dsmtpd-1.2.0.dist-info/RECORD
