Metadata-Version: 2.4
Name: dsmtpd
Version: 1.2.0
Summary: Simple SMTP Server for debugging
Home-page: https://github.com/matrixise/dsmtpd
Author: Stéphane Wirtel
Author-email: stephane@wirtel.be
License: BSD-2-Clause
Project-URL: Source, https://github.com/matrixise/dsmtpd
Project-URL: Tracker, https://github.com/matrixise/dsmtpd/issues
Classifier: Development Status :: 5 - Production/Stable
Classifier: Environment :: Console
Classifier: Intended Audience :: Developers
Classifier: Programming Language :: Python :: 3 :: Only
Classifier: Programming Language :: Python :: 3
Classifier: Programming Language :: Python :: 3.10
Classifier: Programming Language :: Python :: 3.11
Classifier: Programming Language :: Python :: 3.12
Classifier: Programming Language :: Python :: 3.13
Classifier: Programming Language :: Python :: 3.14
Classifier: Topic :: Communications :: Email
Requires-Python: >=3.10
License-File: LICENSE
License-File: AUTHORS
Requires-Dist: aiosmtpd
Dynamic: license-file
